MengJinhuaYujiazhiWanchengVol2/Dockerfile
MengJinhuaYujiazhiWanchengVol2/README.md
MengJinhuaYujiazhiWanchengVol2/__init__.py
MengJinhuaYujiazhiWanchengVol2/__main__.py
MengJinhuaYujiazhiWanchengVol2/file.epub
MengJinhuaYujiazhiWanchengVol2/index.html
MengJinhuaYujiazhiWanchengVol2/css/__init__.py
MengJinhuaYujiazhiWanchengVol2/css/annotations.css
MengJinhuaYujiazhiWanchengVol2/css/main.css
MengJinhuaYujiazhiWanchengVol2/css/normalize.css
MengJinhuaYujiazhiWanchengVol2/css/popup.css
MengJinhuaYujiazhiWanchengVol2/font/__init__.py
MengJinhuaYujiazhiWanchengVol2/font/fontello.eot
MengJinhuaYujiazhiWanchengVol2/font/fontello.svg
MengJinhuaYujiazhiWanchengVol2/font/fontello.ttf
MengJinhuaYujiazhiWanchengVol2/font/fontello.woff
MengJinhuaYujiazhiWanchengVol2/img/__init__.py
MengJinhuaYujiazhiWanchengVol2/img/annotator-glyph-sprite.png
MengJinhuaYujiazhiWanchengVol2/img/annotator-icon-sprite.png
MengJinhuaYujiazhiWanchengVol2/img/apple-touch-icon.png
MengJinhuaYujiazhiWanchengVol2/img/cancelfullscreen.png
MengJinhuaYujiazhiWanchengVol2/img/close.png
MengJinhuaYujiazhiWanchengVol2/img/fullscreen.png
MengJinhuaYujiazhiWanchengVol2/img/loader.gif
MengJinhuaYujiazhiWanchengVol2/img/menu-icon.png
MengJinhuaYujiazhiWanchengVol2/img/save.png
MengJinhuaYujiazhiWanchengVol2/img/saved.png
MengJinhuaYujiazhiWanchengVol2/img/settings-s.png
MengJinhuaYujiazhiWanchengVol2/img/settings.png
MengJinhuaYujiazhiWanchengVol2/img/star.png
MengJinhuaYujiazhiWanchengVol2/js/__init__.py
MengJinhuaYujiazhiWanchengVol2/js/epub.js
MengJinhuaYujiazhiWanchengVol2/js/epub.min.js
MengJinhuaYujiazhiWanchengVol2/js/epub.min.map
MengJinhuaYujiazhiWanchengVol2/js/hooks.min.js
MengJinhuaYujiazhiWanchengVol2/js/hooks.min.map
MengJinhuaYujiazhiWanchengVol2/js/reader.js
MengJinhuaYujiazhiWanchengVol2/js/reader.js.map
MengJinhuaYujiazhiWanchengVol2/js/reader.min.js
MengJinhuaYujiazhiWanchengVol2/js/reader.min.map
MengJinhuaYujiazhiWanchengVol2/js/hooks/__init__.py
meng_jinhua_yujiazhi_wancheng_vol2-2022.10.9.1.dist-info/METADATA
meng_jinhua_yujiazhi_wancheng_vol2-2022.10.9.1.dist-info/WHEEL
meng_jinhua_yujiazhi_wancheng_vol2-2022.10.9.1.dist-info/entry_points.txt
meng_jinhua_yujiazhi_wancheng_vol2-2022.10.9.1.dist-info/top_level.txt
meng_jinhua_yujiazhi_wancheng_vol2-2022.10.9.1.dist-info/RECORD
